notifyon/__init__.py
notifyon/client.py
notifyon/exceptions.py
notifyon-0.1.0.dist-info/licenses/LICENSE
notifyon-0.1.0.dist-info/METADATA
notifyon-0.1.0.dist-info/WHEEL
notifyon-0.1.0.dist-info/top_level.txt
notifyon-0.1.0.dist-info/RECORD
