Metadata-Version: 2.4
Name: notifyon
Version: 0.1.0
Summary: Python SDK for NotifyOn notification service
Home-page: https://github.com/notifyon/python-sdk
Author: NotifyOn
Author-email: NotifyOn <support@notifyon.app>
License: MIT
Project-URL: Homepage, https://notifyon.app
Project-URL: Documentation, https://github.com/notifyon/python-sdk
Project-URL: Repository, https://github.com/notifyon/python-sdk
Project-URL: Issues, https://github.com/notifyon/python-sdk/issues
Classifier: Development Status :: 3 - Alpha
Classifier: Intended Audience :: Developers
Classifier: Topic :: Software Development :: Libraries :: Python Modules
Classifier: License :: OSI Approved :: MIT License
Classifier: Programming Language :: Python :: 3
Classifier: Programming Language :: Python :: 3.7
Classifier: Programming Language :: Python :: 3.8
Classifier: Programming Language :: Python :: 3.9
Classifier: Programming Language :: Python :: 3.10
Classifier: Programming Language :: Python :: 3.11
Classifier: Programming Language :: Python :: 3.12
Requires-Python: >=3.7
License-File: LICENSE
Requires-Dist: requests>=2.25.0
Dynamic: author
Dynamic: home-page
Dynamic: license-file
Dynamic: requires-python
